LICENSE
MANIFEST.in
README.md
setup.py
adldap_sync/__init__.py
adldap_sync/admin.py
adldap_sync/apps.py
adldap_sync/callbacks.py
adldap_sync/models.py
adldap_sync/tasks.py
adldap_sync/management/__init__.py
adldap_sync/management/commands/__init__.py
adldap_sync/management/commands/syncldap.py
django_adldap_sync.egg-info/PKG-INFO
django_adldap_sync.egg-info/SOURCES.txt
django_adldap_sync.egg-info/dependency_links.txt
django_adldap_sync.egg-info/requires.txt
django_adldap_sync.egg-info/top_level.txt
docs/Makefile
docs/changelog.rst
docs/conf.py
docs/index.rst
docs/installation.rst
docs/settings.rst