Metadata-Version: 1.1
Name: django-adldap-sync
Version: 0.5.2
Summary: A Django application for synchronizing LDAP users, groups and group memberships
Home-page: https://github.com/marchete/django-adldap-sync
Author: Marchete
Author-email: undisclosed@gmail.com
License: BSD
Download-URL: https://github.com/marchete/django-adldap-sync
Keywords: django,ldap,active directory,synchronize,sync
Platform: UNKNOWN
Classifier: Development Status :: 3 - Alpha
Classifier: Environment :: Web Environment
Classifier: Programming Language :: Python
Classifier: Framework :: Django
Classifier: Intended Audience :: Developers
Classifier: License :: OSI Approved :: BSD License
Classifier: Operating System :: OS Independent
Classifier: Topic :: Software Development :: Libraries :: Python Modules
Classifier: Topic :: System :: Systems Administration :: Authentication/Directory
